[ {
  "characteristics" : [ {
    "element" : "EntryLevelSystemCall1 (_e_rO8FqtEe2qg-kYolqCnw) of type EntryLevelSystemCall (calling)",
    "nodeCharacteristics" : [ ],
    "dataCharacteristics" : {
      "tax" : [ "IncidentRates.medium", "TaxDifferation.medium" ]
    }
  }, {
    "element" : "TaxAction (_O_YbIFqtEe2qg-kYolqCnw) of type SetVariableAction",
    "context" : "Assembly_CustomSystem (_x35GgBcfEe2S64bq59AiXg)",
    "nodeCharacteristics" : [ ],
    "dataCharacteristics" : {
      "tax" : [ "IncidentRates.medium", "TaxDifferation.medium" ]
    }
  }, {
    "element" : "EntryLevelSystemCall1 (_e_rO8FqtEe2qg-kYolqCnw) of type EntryLevelSystemCall (returning)",
    "nodeCharacteristics" : [ ],
    "dataCharacteristics" : { }
  } ],
  "actionSequence" : [ {
    "context" : [ ],
    "element" : {
      "type" : "EntryLevelSystemCall",
      "name" : "EntryLevelSystemCall1",
      "id" : "_e_rO8FqtEe2qg-kYolqCnw"
    },
    "callingPart" : true,
    "returningPart" : false
  }, {
    "context" : [ {
      "type" : "AssemblyContext",
      "name" : "Assembly_CustomSystem",
      "id" : "_x35GgBcfEe2S64bq59AiXg"
    } ],
    "element" : {
      "type" : "SetVariableAction",
      "name" : "TaxAction",
      "id" : "_O_YbIFqtEe2qg-kYolqCnw"
    }
  }, {
    "context" : [ ],
    "element" : {
      "type" : "EntryLevelSystemCall",
      "name" : "EntryLevelSystemCall1",
      "id" : "_e_rO8FqtEe2qg-kYolqCnw"
    },
    "callingPart" : false,
    "returningPart" : true
  } ]
} ]